Metadata-Version: 2.1
Name: xellusmodule
Version: 0.1.3
Summary: A example Python package
Home-page: https://github.com/xe11us/pyexample
Author: Alexey Vasilyev
Author-email: vasilyev-av22@mail.ru
License: UNKNOWN
Platform: UNKNOWN
License-File: LICENSE
